dysregnet/__init__.py
dysregnet/dysregnet.py
dysregnet/functions.py
dysregnet-0.1.0.dist-info/LICENSE
dysregnet-0.1.0.dist-info/METADATA
dysregnet-0.1.0.dist-info/WHEEL
dysregnet-0.1.0.dist-info/top_level.txt
dysregnet-0.1.0.dist-info/RECORD
