Metadata-Version: 2.1
Name: dysregnet
Version: 0.1.0
Summary: DysRegNet
Home-page: https://github.com/biomedbigdata/DysRegNet_package
Author: Zakaria Louadi, Olga Lazareva, Johannes Kersting
Author-email: zakaria.louadi@tum.de, olga.lazareva@tum.de, johannes.kersting@tum.de
License: GPLv3
Classifier: Programming Language :: Python :: 3
Classifier: Programming Language :: Python :: 3.7
Classifier: Programming Language :: Python :: 3.8
Classifier: Programming Language :: Python :: 3.9
Classifier: Programming Language :: Python :: 3.10
Classifier: Programming Language :: Python :: 3.11
Classifier: License :: OSI Approved :: GNU General Public License v3 (GPLv3)
Classifier: Topic :: Scientific/Engineering :: Bio-Informatics
Requires-Python: >=3.7
License-File: LICENSE
Requires-Dist: pandas
Requires-Dist: numpy >=1.19
Requires-Dist: scipy
Requires-Dist: statsmodels
Requires-Dist: tqdm
Requires-Dist: scikit-learn
